clihttp/__init__.py
clihttp/cli.py
clihttp-1.1.0.dist-info/LICENSE.md
clihttp-1.1.0.dist-info/METADATA
clihttp-1.1.0.dist-info/WHEEL
clihttp-1.1.0.dist-info/entry_points.txt
clihttp-1.1.0.dist-info/top_level.txt
clihttp-1.1.0.dist-info/RECORD
