Metadata-Version: 2.2
Name: clihttp
Version: 1.1.0
Summary: A simple Python module to make HTTP requests using command line.
Home-page: https://github.com/kshvsec/clihttp
Author: K5HV
Classifier: Programming Language :: Python :: 3
Classifier: License :: OSI Approved :: MIT License
Classifier: Operating System :: OS Independent
Requires-Python: >=3.6
License-File: LICENSE.md
Requires-Dist: requests
Dynamic: author
Dynamic: classifier
Dynamic: description
Dynamic: description-content-type
Dynamic: home-page
Dynamic: requires-dist
Dynamic: requires-python
Dynamic: summary
